<?xml version="1.0" standalone="yes"?>
<?program_dtd version="1"?>

<PROGRAM NAME="dvt3_doom_PIC_descrambled.rev_2byte.bin" EXE_PATH="dvt3_doom_PIC_descrambled.rev_2byte.bin" EXE_FORMAT="Binary file" INPUT_MD5="5&#xeb;&amp;B&#xa7;&#x81;m\K&#xde;&#xc3;&#xb3;&#xa9;&#xad;&#xfd;">
    <INFO_SOURCE TOOL="IDA-Pro 8.3 XML plugin v5.0.2 (Python) SDK 830" USER="DiscoStarslayer" FILE="PIC_B2A.idb" TIMESTAMP="2025-05-02 11:57" />
    <PROCESSOR NAME="PIC16Cxx" ENDIAN="little" ADDRESS_MODEL="16-bit" />
    <COMPILER NAME="Unknown" />
    <MEMORY_MAP>
        <MEMORY_SECTION NAME="CODE" START_ADDR="CODE:0000" LENGTH="0x2000">
            <MEMORY_CONTENTS START_ADDR="CODE:0000" FILE_NAME="../PIC_B2A.bin" FILE_OFFSET="0x0" LENGTH="0x2000" />
        </MEMORY_SECTION>
        <MEMORY_SECTION NAME="DATA" START_ADDR="DATA:0000" LENGTH="0x400" />
    </MEMORY_MAP>
    <REGISTER_VALUES>
        <REGISTER_VALUE_RANGE REGISTER="bank" VALUE="0x0" START_ADDRESS="CODE:0000" LENGTH="0xE" />
        <REGISTER_VALUE_RANGE REGISTER="bank" VALUE="0x0" START_ADDRESS="CODE:0007" LENGTH="0x16" />
        <REGISTER_VALUE_RANGE REGISTER="bank" VALUE="0x0" START_ADDRESS="CODE:0012" LENGTH="0x2" />
        <REGISTER_VALUE_RANGE REGISTER="bank" VALUE="0x0" START_ADDRESS="CODE:0013" LENGTH="0x2" />
        <REGISTER_VALUE_RANGE REGISTER="bank" VALUE="0x0" START_ADDRESS="CODE:0014" LENGTH="0x6" />
        <REGISTER_VALUE_RANGE REGISTER="bank" VALUE="0x0" START_ADDRESS="CODE:0017" LENGTH="0x4" />
        <REGISTER_VALUE_RANGE REGISTER="bank" VALUE="0x1" START_ADDRESS="CODE:0019" LENGTH="0x4" />
        <REGISTER_VALUE_RANGE REGISTER="bank" VALUE="0x0" START_ADDRESS="CODE:001B" LENGTH="0x8" />
        <REGISTER_VALUE_RANGE REGISTER="bank" VALUE="0x0" START_ADDRESS="CODE:001F" LENGTH="0xE" />
        <REGISTER_VALUE_RANGE REGISTER="bank" VALUE="0x0" START_ADDRESS="CODE:0026" LENGTH="0xA" />
        <REGISTER_VALUE_RANGE REGISTER="bank" VALUE="0x0" START_ADDRESS="CODE:002B" LENGTH="0x6" />
        <REGISTER_VALUE_RANGE REGISTER="bank" VALUE="0x0" START_ADDRESS="CODE:002E" LENGTH="0x1C" />
        <REGISTER_VALUE_RANGE REGISTER="bank" VALUE="0x0" START_ADDRESS="CODE:003C" LENGTH="0x4" />
        <REGISTER_VALUE_RANGE REGISTER="bank" VALUE="0x0" START_ADDRESS="CODE:003E" LENGTH="0x6" />
        <REGISTER_VALUE_RANGE REGISTER="bank" VALUE="0x0" START_ADDRESS="CODE:0041" LENGTH="0x4A" />
        <REGISTER_VALUE_RANGE REGISTER="bank" VALUE="0x0" START_ADDRESS="CODE:0066" LENGTH="0x2" />
        <REGISTER_VALUE_RANGE REGISTER="bank" VALUE="0x0" START_ADDRESS="CODE:0067" LENGTH="0x18" />
        <REGISTER_VALUE_RANGE REGISTER="bank" VALUE="0x0" START_ADDRESS="CODE:0073" LENGTH="0x8" />
        <REGISTER_VALUE_RANGE REGISTER="bank" VALUE="0x0" START_ADDRESS="CODE:0077" LENGTH="0x8" />
        <REGISTER_VALUE_RANGE REGISTER="bank" VALUE="0x0" START_ADDRESS="CODE:007B" LENGTH="0xA" />
        <REGISTER_VALUE_RANGE REGISTER="bank" VALUE="0x0" START_ADDRESS="CODE:0080" LENGTH="0x2" />
        <REGISTER_VALUE_RANGE REGISTER="bank" VALUE="0x0" START_ADDRESS="CODE:0081" LENGTH="0xE" />
        <REGISTER_VALUE_RANGE REGISTER="bank" VALUE="0x0" START_ADDRESS="CODE:0088" LENGTH="0x8" />
        <REGISTER_VALUE_RANGE REGISTER="bank" VALUE="0x0" START_ADDRESS="CODE:008C" LENGTH="0x2" />
        <REGISTER_VALUE_RANGE REGISTER="bank" VALUE="0x0" START_ADDRESS="CODE:008D" LENGTH="0x2" />
        <REGISTER_VALUE_RANGE REGISTER="bank" VALUE="0x0" START_ADDRESS="CODE:008E" LENGTH="0x2" />
        <REGISTER_VALUE_RANGE REGISTER="bank" VALUE="0x0" START_ADDRESS="CODE:008F" LENGTH="0x2" />
        <REGISTER_VALUE_RANGE REGISTER="bank" VALUE="0x0" START_ADDRESS="CODE:0090" LENGTH="0x6" />
        <REGISTER_VALUE_RANGE REGISTER="bank" VALUE="0x0" START_ADDRESS="CODE:0093" LENGTH="0x6" />
        <REGISTER_VALUE_RANGE REGISTER="bank" VALUE="0x0" START_ADDRESS="CODE:0096" LENGTH="0x2" />
        <REGISTER_VALUE_RANGE REGISTER="bank" VALUE="0x0" START_ADDRESS="CODE:0097" LENGTH="0x2" />
        <REGISTER_VALUE_RANGE REGISTER="bank" VALUE="0x0" START_ADDRESS="CODE:0098" LENGTH="0x2" />
        <REGISTER_VALUE_RANGE REGISTER="bank" VALUE="0x0" START_ADDRESS="CODE:0099" LENGTH="0x2" />
        <REGISTER_VALUE_RANGE REGISTER="bank" VALUE="0x0" START_ADDRESS="CODE:009A" LENGTH="0x6" />
        <REGISTER_VALUE_RANGE REGISTER="bank" VALUE="0x0" START_ADDRESS="CODE:009D" LENGTH="0x6" />
        <REGISTER_VALUE_RANGE REGISTER="bank" VALUE="0x0" START_ADDRESS="CODE:00A0" LENGTH="0x8" />
        <REGISTER_VALUE_RANGE REGISTER="bank" VALUE="0x0" START_ADDRESS="CODE:00A4" LENGTH="0x2" />
        <REGISTER_VALUE_RANGE REGISTER="bank" VALUE="0x0" START_ADDRESS="CODE:00A5" LENGTH="0x2" />
        <REGISTER_VALUE_RANGE REGISTER="bank" VALUE="0x0" START_ADDRESS="CODE:00A6" LENGTH="0x6" />
        <REGISTER_VALUE_RANGE REGISTER="bank" VALUE="0x0" START_ADDRESS="CODE:00A9" LENGTH="0x6" />
        <REGISTER_VALUE_RANGE REGISTER="bank" VALUE="0x0" START_ADDRESS="CODE:00AC" LENGTH="0x6" />
        <REGISTER_VALUE_RANGE REGISTER="bank" VALUE="0x0" START_ADDRESS="CODE:00AF" LENGTH="0x6" />
        <REGISTER_VALUE_RANGE REGISTER="bank" VALUE="0x0" START_ADDRESS="CODE:00B2" LENGTH="0x2" />
        <REGISTER_VALUE_RANGE REGISTER="bank" VALUE="0x0" START_ADDRESS="CODE:00B3" LENGTH="0x2" />
        <REGISTER_VALUE_RANGE REGISTER="bank" VALUE="0x0" START_ADDRESS="CODE:00B4" LENGTH="0x8" />
        <REGISTER_VALUE_RANGE REGISTER="bank" VALUE="0x1" START_ADDRESS="CODE:00B8" LENGTH="0x6" />
        <REGISTER_VALUE_RANGE REGISTER="bank" VALUE="0x0" START_ADDRESS="CODE:00BB" LENGTH="0x8" />
        <REGISTER_VALUE_RANGE REGISTER="bank" VALUE="0x1" START_ADDRESS="CODE:00BF" LENGTH="0xA" />
        <REGISTER_VALUE_RANGE REGISTER="bank" VALUE="0x0" START_ADDRESS="CODE:00C4" LENGTH="0x2" />
        <REGISTER_VALUE_RANGE REGISTER="bank" VALUE="0x0" START_ADDRESS="CODE:00C5" LENGTH="0x5A" />
        <REGISTER_VALUE_RANGE REGISTER="bank" VALUE="0x0" START_ADDRESS="CODE:00F2" LENGTH="0x2" />
        <REGISTER_VALUE_RANGE REGISTER="bank" VALUE="0x0" START_ADDRESS="CODE:00F3" LENGTH="0x2" />
        <REGISTER_VALUE_RANGE REGISTER="bank" VALUE="0x0" START_ADDRESS="CODE:00F4" LENGTH="0xA" />
        <REGISTER_VALUE_RANGE REGISTER="bank" VALUE="0x0" START_ADDRESS="CODE:00F9" LENGTH="0x2" />
        <REGISTER_VALUE_RANGE REGISTER="bank" VALUE="0x0" START_ADDRESS="CODE:00FA" LENGTH="0x2" />
        <REGISTER_VALUE_RANGE REGISTER="bank" VALUE="0x0" START_ADDRESS="CODE:00FB" LENGTH="0x8" />
        <REGISTER_VALUE_RANGE REGISTER="bank" VALUE="0x0" START_ADDRESS="CODE:00FF" LENGTH="0x10" />
        <REGISTER_VALUE_RANGE REGISTER="bank" VALUE="0x0" START_ADDRESS="CODE:0107" LENGTH="0x6" />
        <REGISTER_VALUE_RANGE REGISTER="bank" VALUE="0x0" START_ADDRESS="CODE:010A" LENGTH="0xA" />
        <REGISTER_VALUE_RANGE REGISTER="bank" VALUE="0x0" START_ADDRESS="CODE:010F" LENGTH="0x16" />
        <REGISTER_VALUE_RANGE REGISTER="bank" VALUE="0x0" START_ADDRESS="CODE:011A" LENGTH="0x2" />
        <REGISTER_VALUE_RANGE REGISTER="bank" VALUE="0x0" START_ADDRESS="CODE:011B" LENGTH="0x2" />
        <REGISTER_VALUE_RANGE REGISTER="bank" VALUE="0x0" START_ADDRESS="CODE:011C" LENGTH="0xA" />
        <REGISTER_VALUE_RANGE REGISTER="bank" VALUE="0x0" START_ADDRESS="CODE:0121" LENGTH="0xA" />
        <REGISTER_VALUE_RANGE REGISTER="bank" VALUE="0x0" START_ADDRESS="CODE:0126" LENGTH="0x18" />
        <REGISTER_VALUE_RANGE REGISTER="bank" VALUE="0x0" START_ADDRESS="CODE:0132" LENGTH="0x6" />
        <REGISTER_VALUE_RANGE REGISTER="bank" VALUE="0x0" START_ADDRESS="CODE:0135" LENGTH="0x2" />
        <REGISTER_VALUE_RANGE REGISTER="bank" VALUE="0x0" START_ADDRESS="CODE:0136" LENGTH="0x2" />
        <REGISTER_VALUE_RANGE REGISTER="bank" VALUE="0x0" START_ADDRESS="CODE:0137" LENGTH="0x2" />
        <REGISTER_VALUE_RANGE REGISTER="bank" VALUE="0x0" START_ADDRESS="CODE:0138" LENGTH="0x22" />
        <REGISTER_VALUE_RANGE REGISTER="bank" VALUE="0x0" START_ADDRESS="CODE:0149" LENGTH="0xA" />
        <REGISTER_VALUE_RANGE REGISTER="bank" VALUE="0x0" START_ADDRESS="CODE:014E" LENGTH="0xA" />
        <REGISTER_VALUE_RANGE REGISTER="bank" VALUE="0x0" START_ADDRESS="CODE:0153" LENGTH="0x6" />
        <REGISTER_VALUE_RANGE REGISTER="bank" VALUE="0x0" START_ADDRESS="CODE:0156" LENGTH="0x2" />
        <REGISTER_VALUE_RANGE REGISTER="bank" VALUE="0x0" START_ADDRESS="CODE:0157" LENGTH="0x2" />
        <REGISTER_VALUE_RANGE REGISTER="bank" VALUE="0x0" START_ADDRESS="CODE:0158" LENGTH="0x2" />
        <REGISTER_VALUE_RANGE REGISTER="bank" VALUE="0x0" START_ADDRESS="CODE:0159" LENGTH="0x2" />
        <REGISTER_VALUE_RANGE REGISTER="bank" VALUE="0x0" START_ADDRESS="CODE:015A" LENGTH="0x16" />
        <REGISTER_VALUE_RANGE REGISTER="bank" VALUE="0x0" START_ADDRESS="CODE:0165" LENGTH="0xC" />
        <REGISTER_VALUE_RANGE REGISTER="bank" VALUE="0x0" START_ADDRESS="CODE:016B" LENGTH="0x6" />
        <REGISTER_VALUE_RANGE REGISTER="bank" VALUE="0x0" START_ADDRESS="CODE:016E" LENGTH="0x2" />
        <REGISTER_VALUE_RANGE REGISTER="bank" VALUE="0x0" START_ADDRESS="CODE:016F" LENGTH="0xC" />
        <REGISTER_VALUE_RANGE REGISTER="bank" VALUE="0x0" START_ADDRESS="CODE:0175" LENGTH="0x8" />
        <REGISTER_VALUE_RANGE REGISTER="bank" VALUE="0x0" START_ADDRESS="CODE:0179" LENGTH="0x6" />
        <REGISTER_VALUE_RANGE REGISTER="bank" VALUE="0x0" START_ADDRESS="CODE:017C" LENGTH="0x2" />
        <REGISTER_VALUE_RANGE REGISTER="bank" VALUE="0x1" START_ADDRESS="CODE:017D" LENGTH="0x6" />
        <REGISTER_VALUE_RANGE REGISTER="bank" VALUE="0x0" START_ADDRESS="CODE:0180" LENGTH="0xA" />
        <REGISTER_VALUE_RANGE REGISTER="bank" VALUE="0x1" START_ADDRESS="CODE:0185" LENGTH="0x2" />
        <REGISTER_VALUE_RANGE REGISTER="bank" VALUE="0x0" START_ADDRESS="CODE:0186" LENGTH="0x4" />
        <REGISTER_VALUE_RANGE REGISTER="bank" VALUE="0x0" START_ADDRESS="CODE:0188" LENGTH="0x14" />
        <REGISTER_VALUE_RANGE REGISTER="bank" VALUE="0x0" START_ADDRESS="CODE:0192" LENGTH="0x4" />
        <REGISTER_VALUE_RANGE REGISTER="bank" VALUE="0x0" START_ADDRESS="CODE:0194" LENGTH="0x10" />
        <REGISTER_VALUE_RANGE REGISTER="bank" VALUE="0x0" START_ADDRESS="CODE:019C" LENGTH="0x4" />
        <REGISTER_VALUE_RANGE REGISTER="bank" VALUE="0x0" START_ADDRESS="CODE:019E" LENGTH="0x2" />
        <REGISTER_VALUE_RANGE REGISTER="bank" VALUE="0x1" START_ADDRESS="CODE:019F" LENGTH="0x6" />
        <REGISTER_VALUE_RANGE REGISTER="bank" VALUE="0x0" START_ADDRESS="CODE:01A2" LENGTH="0xA" />
        <REGISTER_VALUE_RANGE REGISTER="bank" VALUE="0x1" START_ADDRESS="CODE:01A7" LENGTH="0x2" />
        <REGISTER_VALUE_RANGE REGISTER="bank" VALUE="0x0" START_ADDRESS="CODE:01A8" LENGTH="0x4" />
        <REGISTER_VALUE_RANGE REGISTER="bank" VALUE="0x0" START_ADDRESS="CODE:01AA" LENGTH="0x2" />
        <REGISTER_VALUE_RANGE REGISTER="bank" VALUE="0x0" START_ADDRESS="CODE:01AB" LENGTH="0x6" />
        <REGISTER_VALUE_RANGE REGISTER="bank" VALUE="0x0" START_ADDRESS="CODE:01AE" LENGTH="0x2" />
        <REGISTER_VALUE_RANGE REGISTER="bank" VALUE="0x1" START_ADDRESS="CODE:01AF" LENGTH="0x4" />
        <REGISTER_VALUE_RANGE REGISTER="bank" VALUE="0x0" START_ADDRESS="CODE:01B1" LENGTH="0xC" />
        <REGISTER_VALUE_RANGE REGISTER="bank" VALUE="0x0" START_ADDRESS="CODE:01B7" LENGTH="0x8" />
        <REGISTER_VALUE_RANGE REGISTER="bank" VALUE="0x1" START_ADDRESS="CODE:01BB" LENGTH="0x6" />
        <REGISTER_VALUE_RANGE REGISTER="bank" VALUE="0x0" START_ADDRESS="CODE:01BE" LENGTH="0xC" />
        <REGISTER_VALUE_RANGE REGISTER="bank" VALUE="0x1" START_ADDRESS="CODE:01C4" LENGTH="0x6" />
        <REGISTER_VALUE_RANGE REGISTER="bank" VALUE="0x0" START_ADDRESS="CODE:01C7" LENGTH="0x2" />
        <REGISTER_VALUE_RANGE REGISTER="bank" VALUE="0x1" START_ADDRESS="CODE:01C8" LENGTH="0x6" />
        <REGISTER_VALUE_RANGE REGISTER="bank" VALUE="0x0" START_ADDRESS="CODE:01CB" LENGTH="0x4" />
        <REGISTER_VALUE_RANGE REGISTER="bank" VALUE="0x0" START_ADDRESS="CODE:01CD" LENGTH="0x14" />
        <REGISTER_VALUE_RANGE REGISTER="bank" VALUE="0x0" START_ADDRESS="CODE:01D7" LENGTH="0x32" />
        <REGISTER_VALUE_RANGE REGISTER="bank" VALUE="0x1" START_ADDRESS="CODE:01F0" LENGTH="0x6" />
        <REGISTER_VALUE_RANGE REGISTER="bank" VALUE="0x0" START_ADDRESS="CODE:01F3" LENGTH="0x2" />
        <REGISTER_VALUE_RANGE REGISTER="bank" VALUE="0x0" START_ADDRESS="CODE:01F4" LENGTH="0x1C" />
        <REGISTER_VALUE_RANGE REGISTER="bank" VALUE="0x1" START_ADDRESS="CODE:0202" LENGTH="0x6" />
        <REGISTER_VALUE_RANGE REGISTER="bank" VALUE="0x0" START_ADDRESS="CODE:0205" LENGTH="0x2" />
        <REGISTER_VALUE_RANGE REGISTER="bank" VALUE="0x0" START_ADDRESS="CODE:0206" LENGTH="0x32E" />
        <REGISTER_VALUE_RANGE REGISTER="bank" VALUE="0x0" START_ADDRESS="CODE:039D" LENGTH="0x260" />
        <REGISTER_VALUE_RANGE REGISTER="bank" VALUE="0x0" START_ADDRESS="CODE:04CD" LENGTH="0xE6" />
        <REGISTER_VALUE_RANGE REGISTER="bank" VALUE="0x0" START_ADDRESS="CODE:0540" LENGTH="0x50" />
        <REGISTER_VALUE_RANGE REGISTER="bank" VALUE="0x0" START_ADDRESS="CODE:0568" LENGTH="0x50" />
        <REGISTER_VALUE_RANGE REGISTER="bank" VALUE="0x0" START_ADDRESS="CODE:0590" LENGTH="0x5C" />
        <REGISTER_VALUE_RANGE REGISTER="bank" VALUE="0x0" START_ADDRESS="CODE:05BE" LENGTH="0x78" />
        <REGISTER_VALUE_RANGE REGISTER="bank" VALUE="0x0" START_ADDRESS="CODE:05FA" LENGTH="0x7E" />
        <REGISTER_VALUE_RANGE REGISTER="bank" VALUE="0x0" START_ADDRESS="CODE:0639" LENGTH="0xA0" />
        <REGISTER_VALUE_RANGE REGISTER="bank" VALUE="0x0" START_ADDRESS="CODE:0689" LENGTH="0x2EE" />
        <REGISTER_VALUE_RANGE REGISTER="bank" VALUE="0x0" START_ADDRESS="CODE:0800" LENGTH="0xDC" />
        <REGISTER_VALUE_RANGE REGISTER="bank" VALUE="0x0" START_ADDRESS="CODE:086E" LENGTH="0x94" />
        <REGISTER_VALUE_RANGE REGISTER="bank" VALUE="0x0" START_ADDRESS="CODE:08B8" LENGTH="0x16C" />
        <REGISTER_VALUE_RANGE REGISTER="bank" VALUE="0x0" START_ADDRESS="CODE:096E" LENGTH="0x1D4" />
        <REGISTER_VALUE_RANGE REGISTER="bank" VALUE="0x0" START_ADDRESS="CODE:0A58" LENGTH="0xC" />
        <REGISTER_VALUE_RANGE REGISTER="bank" VALUE="0x1" START_ADDRESS="CODE:0A5E" LENGTH="0x4" />
        <REGISTER_VALUE_RANGE REGISTER="bank" VALUE="0x0" START_ADDRESS="CODE:0A60" LENGTH="0xA" />
        <REGISTER_VALUE_RANGE REGISTER="bank" VALUE="0x0" START_ADDRESS="CODE:0A65" LENGTH="0xB36" />
        <REGISTER_VALUE_RANGE REGISTER="bank" VALUE="0x0" START_ADDRESS="DATA:0000" LENGTH="0x400" />
        <REGISTER_VALUE_RANGE REGISTER="ds" VALUE="0x0" START_ADDRESS="CODE:0000" LENGTH="0x2000" />
        <REGISTER_VALUE_RANGE REGISTER="pclath" VALUE="0x0" START_ADDRESS="CODE:0000" LENGTH="0x2" />
        <REGISTER_VALUE_RANGE REGISTER="pclath" VALUE="0x0" START_ADDRESS="CODE:0001" LENGTH="0x18" />
        <REGISTER_VALUE_RANGE REGISTER="pclath" VALUE="0x0" START_ADDRESS="CODE:000D" LENGTH="0xA" />
        <REGISTER_VALUE_RANGE REGISTER="pclath" VALUE="0x0" START_ADDRESS="CODE:0012" LENGTH="0x2" />
        <REGISTER_VALUE_RANGE REGISTER="pclath" VALUE="0x0" START_ADDRESS="CODE:0013" LENGTH="0x2" />
        <REGISTER_VALUE_RANGE REGISTER="pclath" VALUE="0x0" START_ADDRESS="CODE:0014" LENGTH="0x6" />
        <REGISTER_VALUE_RANGE REGISTER="pclath" VALUE="0x0" START_ADDRESS="CODE:0017" LENGTH="0x10" />
        <REGISTER_VALUE_RANGE REGISTER="pclath" VALUE="0x0" START_ADDRESS="CODE:001F" LENGTH="0xE" />
        <REGISTER_VALUE_RANGE REGISTER="pclath" VALUE="0x0" START_ADDRESS="CODE:0026" LENGTH="0xA" />
        <REGISTER_VALUE_RANGE REGISTER="pclath" VALUE="0x0" START_ADDRESS="CODE:002B" LENGTH="0x6" />
        <REGISTER_VALUE_RANGE REGISTER="pclath" VALUE="0x0" START_ADDRESS="CODE:002E" LENGTH="0x1C" />
        <REGISTER_VALUE_RANGE REGISTER="pclath" VALUE="0x0" START_ADDRESS="CODE:003C" LENGTH="0x4" />
        <REGISTER_VALUE_RANGE REGISTER="pclath" VALUE="0x0" START_ADDRESS="CODE:003E" LENGTH="0x6" />
        <REGISTER_VALUE_RANGE REGISTER="pclath" VALUE="0x0" START_ADDRESS="CODE:0041" LENGTH="0x12" />
        <REGISTER_VALUE_RANGE REGISTER="pclath" VALUE="0x0" START_ADDRESS="CODE:004A" LENGTH="0x38" />
        <REGISTER_VALUE_RANGE REGISTER="pclath" VALUE="0x0" START_ADDRESS="CODE:0066" LENGTH="0x2" />
        <REGISTER_VALUE_RANGE REGISTER="pclath" VALUE="0x0" START_ADDRESS="CODE:0067" LENGTH="0x18" />
        <REGISTER_VALUE_RANGE REGISTER="pclath" VALUE="0x0" START_ADDRESS="CODE:0073" LENGTH="0x8" />
        <REGISTER_VALUE_RANGE REGISTER="pclath" VALUE="0x0" START_ADDRESS="CODE:0077" LENGTH="0x8" />
        <REGISTER_VALUE_RANGE REGISTER="pclath" VALUE="0x0" START_ADDRESS="CODE:007B" LENGTH="0xA" />
        <REGISTER_VALUE_RANGE REGISTER="pclath" VALUE="0x0" START_ADDRESS="CODE:0080" LENGTH="0x2" />
        <REGISTER_VALUE_RANGE REGISTER="pclath" VALUE="0x0" START_ADDRESS="CODE:0081" LENGTH="0xE" />
        <REGISTER_VALUE_RANGE REGISTER="pclath" VALUE="0x0" START_ADDRESS="CODE:0088" LENGTH="0x8" />
        <REGISTER_VALUE_RANGE REGISTER="pclath" VALUE="0x0" START_ADDRESS="CODE:008C" LENGTH="0x2" />
        <REGISTER_VALUE_RANGE REGISTER="pclath" VALUE="0x0" START_ADDRESS="CODE:008D" LENGTH="0x2" />
        <REGISTER_VALUE_RANGE REGISTER="pclath" VALUE="0x0" START_ADDRESS="CODE:008E" LENGTH="0x2" />
        <REGISTER_VALUE_RANGE REGISTER="pclath" VALUE="0x0" START_ADDRESS="CODE:008F" LENGTH="0x2" />
        <REGISTER_VALUE_RANGE REGISTER="pclath" VALUE="0x0" START_ADDRESS="CODE:0090" LENGTH="0x6" />
        <REGISTER_VALUE_RANGE REGISTER="pclath" VALUE="0x0" START_ADDRESS="CODE:0093" LENGTH="0x6" />
        <REGISTER_VALUE_RANGE REGISTER="pclath" VALUE="0x0" START_ADDRESS="CODE:0096" LENGTH="0x2" />
        <REGISTER_VALUE_RANGE REGISTER="pclath" VALUE="0x0" START_ADDRESS="CODE:0097" LENGTH="0x2" />
        <REGISTER_VALUE_RANGE REGISTER="pclath" VALUE="0x0" START_ADDRESS="CODE:0098" LENGTH="0x2" />
        <REGISTER_VALUE_RANGE REGISTER="pclath" VALUE="0x0" START_ADDRESS="CODE:0099" LENGTH="0x2" />
        <REGISTER_VALUE_RANGE REGISTER="pclath" VALUE="0x0" START_ADDRESS="CODE:009A" LENGTH="0x6" />
        <REGISTER_VALUE_RANGE REGISTER="pclath" VALUE="0x0" START_ADDRESS="CODE:009D" LENGTH="0x6" />
        <REGISTER_VALUE_RANGE REGISTER="pclath" VALUE="0x0" START_ADDRESS="CODE:00A0" LENGTH="0x8" />
        <REGISTER_VALUE_RANGE REGISTER="pclath" VALUE="0x0" START_ADDRESS="CODE:00A4" LENGTH="0x2" />
        <REGISTER_VALUE_RANGE REGISTER="pclath" VALUE="0x0" START_ADDRESS="CODE:00A5" LENGTH="0x2" />
        <REGISTER_VALUE_RANGE REGISTER="pclath" VALUE="0x0" START_ADDRESS="CODE:00A6" LENGTH="0x6" />
        <REGISTER_VALUE_RANGE REGISTER="pclath" VALUE="0x0" START_ADDRESS="CODE:00A9" LENGTH="0x6" />
        <REGISTER_VALUE_RANGE REGISTER="pclath" VALUE="0x0" START_ADDRESS="CODE:00AC" LENGTH="0x6" />
        <REGISTER_VALUE_RANGE REGISTER="pclath" VALUE="0x0" START_ADDRESS="CODE:00AF" LENGTH="0x6" />
        <REGISTER_VALUE_RANGE REGISTER="pclath" VALUE="0x0" START_ADDRESS="CODE:00B2" LENGTH="0x2" />
        <REGISTER_VALUE_RANGE REGISTER="pclath" VALUE="0x0" START_ADDRESS="CODE:00B3" LENGTH="0x2" />
        <REGISTER_VALUE_RANGE REGISTER="pclath" VALUE="0x0" START_ADDRESS="CODE:00B4" LENGTH="0x22" />
        <REGISTER_VALUE_RANGE REGISTER="pclath" VALUE="0x0" START_ADDRESS="CODE:00C5" LENGTH="0x22" />
        <REGISTER_VALUE_RANGE REGISTER="pclath" VALUE="0x0" START_ADDRESS="CODE:00D6" LENGTH="0x38" />
        <REGISTER_VALUE_RANGE REGISTER="pclath" VALUE="0x0" START_ADDRESS="CODE:00F2" LENGTH="0x2" />
        <REGISTER_VALUE_RANGE REGISTER="pclath" VALUE="0x0" START_ADDRESS="CODE:00F3" LENGTH="0x2" />
        <REGISTER_VALUE_RANGE REGISTER="pclath" VALUE="0x0" START_ADDRESS="CODE:00F4" LENGTH="0xA" />
        <REGISTER_VALUE_RANGE REGISTER="pclath" VALUE="0x0" START_ADDRESS="CODE:00F9" LENGTH="0x2" />
        <REGISTER_VALUE_RANGE REGISTER="pclath" VALUE="0x0" START_ADDRESS="CODE:00FA" LENGTH="0x2" />
        <REGISTER_VALUE_RANGE REGISTER="pclath" VALUE="0x0" START_ADDRESS="CODE:00FB" LENGTH="0x8" />
        <REGISTER_VALUE_RANGE REGISTER="pclath" VALUE="0x0" START_ADDRESS="CODE:00FF" LENGTH="0x10" />
        <REGISTER_VALUE_RANGE REGISTER="pclath" VALUE="0x0" START_ADDRESS="CODE:0107" LENGTH="0x6" />
        <REGISTER_VALUE_RANGE REGISTER="pclath" VALUE="0x0" START_ADDRESS="CODE:010A" LENGTH="0xA" />
        <REGISTER_VALUE_RANGE REGISTER="pclath" VALUE="0x0" START_ADDRESS="CODE:010F" LENGTH="0x16" />
        <REGISTER_VALUE_RANGE REGISTER="pclath" VALUE="0x0" START_ADDRESS="CODE:011A" LENGTH="0x2" />
        <REGISTER_VALUE_RANGE REGISTER="pclath" VALUE="0x0" START_ADDRESS="CODE:011B" LENGTH="0x2" />
        <REGISTER_VALUE_RANGE REGISTER="pclath" VALUE="0x0" START_ADDRESS="CODE:011C" LENGTH="0xA" />
        <REGISTER_VALUE_RANGE REGISTER="pclath" VALUE="0x0" START_ADDRESS="CODE:0121" LENGTH="0xA" />
        <REGISTER_VALUE_RANGE REGISTER="pclath" VALUE="0x0" START_ADDRESS="CODE:0126" LENGTH="0x18" />
        <REGISTER_VALUE_RANGE REGISTER="pclath" VALUE="0x0" START_ADDRESS="CODE:0132" LENGTH="0x6" />
        <REGISTER_VALUE_RANGE REGISTER="pclath" VALUE="0x0" START_ADDRESS="CODE:0135" LENGTH="0x2" />
        <REGISTER_VALUE_RANGE REGISTER="pclath" VALUE="0x0" START_ADDRESS="CODE:0136" LENGTH="0x2" />
        <REGISTER_VALUE_RANGE REGISTER="pclath" VALUE="0x0" START_ADDRESS="CODE:0137" LENGTH="0x2" />
        <REGISTER_VALUE_RANGE REGISTER="pclath" VALUE="0x0" START_ADDRESS="CODE:0138" LENGTH="0x22" />
        <REGISTER_VALUE_RANGE REGISTER="pclath" VALUE="0x0" START_ADDRESS="CODE:0149" LENGTH="0xA" />
        <REGISTER_VALUE_RANGE REGISTER="pclath" VALUE="0x0" START_ADDRESS="CODE:014E" LENGTH="0xA" />
        <REGISTER_VALUE_RANGE REGISTER="pclath" VALUE="0x0" START_ADDRESS="CODE:0153" LENGTH="0x6" />
        <REGISTER_VALUE_RANGE REGISTER="pclath" VALUE="0x0" START_ADDRESS="CODE:0156" LENGTH="0x2" />
        <REGISTER_VALUE_RANGE REGISTER="pclath" VALUE="0x0" START_ADDRESS="CODE:0157" LENGTH="0x2" />
        <REGISTER_VALUE_RANGE REGISTER="pclath" VALUE="0x0" START_ADDRESS="CODE:0158" LENGTH="0x2" />
        <REGISTER_VALUE_RANGE REGISTER="pclath" VALUE="0x0" START_ADDRESS="CODE:0159" LENGTH="0x2" />
        <REGISTER_VALUE_RANGE REGISTER="pclath" VALUE="0x0" START_ADDRESS="CODE:015A" LENGTH="0x16" />
        <REGISTER_VALUE_RANGE REGISTER="pclath" VALUE="0x0" START_ADDRESS="CODE:0165" LENGTH="0xC" />
        <REGISTER_VALUE_RANGE REGISTER="pclath" VALUE="0x0" START_ADDRESS="CODE:016B" LENGTH="0x6" />
        <REGISTER_VALUE_RANGE REGISTER="pclath" VALUE="0x0" START_ADDRESS="CODE:016E" LENGTH="0xA" />
        <REGISTER_VALUE_RANGE REGISTER="pclath" VALUE="0x0" START_ADDRESS="CODE:0173" LENGTH="0xC" />
        <REGISTER_VALUE_RANGE REGISTER="pclath" VALUE="0x0" START_ADDRESS="CODE:0179" LENGTH="0x6" />
        <REGISTER_VALUE_RANGE REGISTER="pclath" VALUE="0x0" START_ADDRESS="CODE:017C" LENGTH="0x12" />
        <REGISTER_VALUE_RANGE REGISTER="pclath" VALUE="0x0" START_ADDRESS="CODE:0185" LENGTH="0x6" />
        <REGISTER_VALUE_RANGE REGISTER="pclath" VALUE="0x0" START_ADDRESS="CODE:0188" LENGTH="0x14" />
        <REGISTER_VALUE_RANGE REGISTER="pclath" VALUE="0x0" START_ADDRESS="CODE:0192" LENGTH="0x4" />
        <REGISTER_VALUE_RANGE REGISTER="pclath" VALUE="0x0" START_ADDRESS="CODE:0194" LENGTH="0x10" />
        <REGISTER_VALUE_RANGE REGISTER="pclath" VALUE="0x0" START_ADDRESS="CODE:019C" LENGTH="0x4" />
        <REGISTER_VALUE_RANGE REGISTER="pclath" VALUE="0x0" START_ADDRESS="CODE:019E" LENGTH="0x12" />
        <REGISTER_VALUE_RANGE REGISTER="pclath" VALUE="0x0" START_ADDRESS="CODE:01A7" LENGTH="0x6" />
        <REGISTER_VALUE_RANGE REGISTER="pclath" VALUE="0x0" START_ADDRESS="CODE:01AA" LENGTH="0x2" />
        <REGISTER_VALUE_RANGE REGISTER="pclath" VALUE="0x0" START_ADDRESS="CODE:01AB" LENGTH="0x6" />
        <REGISTER_VALUE_RANGE REGISTER="pclath" VALUE="0x0" START_ADDRESS="CODE:01AE" LENGTH="0x12" />
        <REGISTER_VALUE_RANGE REGISTER="pclath" VALUE="0x0" START_ADDRESS="CODE:01B7" LENGTH="0x2C" />
        <REGISTER_VALUE_RANGE REGISTER="pclath" VALUE="0x0" START_ADDRESS="CODE:01CD" LENGTH="0x8" />
        <REGISTER_VALUE_RANGE REGISTER="pclath" VALUE="0x8" START_ADDRESS="CODE:01D1" LENGTH="0x4" />
        <REGISTER_VALUE_RANGE REGISTER="pclath" VALUE="0x0" START_ADDRESS="CODE:01D3" LENGTH="0x8" />
        <REGISTER_VALUE_RANGE REGISTER="pclath" VALUE="0x0" START_ADDRESS="CODE:01D7" LENGTH="0x4" />
        <REGISTER_VALUE_RANGE REGISTER="pclath" VALUE="0x8" START_ADDRESS="CODE:01D9" LENGTH="0x8" />
        <REGISTER_VALUE_RANGE REGISTER="pclath" VALUE="0x0" START_ADDRESS="CODE:01DD" LENGTH="0xE" />
        <REGISTER_VALUE_RANGE REGISTER="pclath" VALUE="0x8" START_ADDRESS="CODE:01E4" LENGTH="0x4" />
        <REGISTER_VALUE_RANGE REGISTER="pclath" VALUE="0x0" START_ADDRESS="CODE:01E6" LENGTH="0xC" />
        <REGISTER_VALUE_RANGE REGISTER="pclath" VALUE="0x8" START_ADDRESS="CODE:01EC" LENGTH="0x4" />
        <REGISTER_VALUE_RANGE REGISTER="pclath" VALUE="0x0" START_ADDRESS="CODE:01EE" LENGTH="0xC" />
        <REGISTER_VALUE_RANGE REGISTER="pclath" VALUE="0x0" START_ADDRESS="CODE:01F4" LENGTH="0x14" />
        <REGISTER_VALUE_RANGE REGISTER="pclath" VALUE="0x8" START_ADDRESS="CODE:01FE" LENGTH="0x4" />
        <REGISTER_VALUE_RANGE REGISTER="pclath" VALUE="0x0" START_ADDRESS="CODE:0200" LENGTH="0xC" />
        <REGISTER_VALUE_RANGE REGISTER="pclath" VALUE="0x0" START_ADDRESS="CODE:0206" LENGTH="0xE" />
        <REGISTER_VALUE_RANGE REGISTER="pclath" VALUE="0x0" START_ADDRESS="CODE:020D" LENGTH="0x320" />
        <REGISTER_VALUE_RANGE REGISTER="pclath" VALUE="0x0" START_ADDRESS="CODE:039D" LENGTH="0xE" />
        <REGISTER_VALUE_RANGE REGISTER="pclath" VALUE="0x0" START_ADDRESS="CODE:03A4" LENGTH="0x252" />
        <REGISTER_VALUE_RANGE REGISTER="pclath" VALUE="0x0" START_ADDRESS="CODE:04CD" LENGTH="0xE" />
        <REGISTER_VALUE_RANGE REGISTER="pclath" VALUE="0x0" START_ADDRESS="CODE:04D4" LENGTH="0xD8" />
        <REGISTER_VALUE_RANGE REGISTER="pclath" VALUE="0x0" START_ADDRESS="CODE:0540" LENGTH="0xE" />
        <REGISTER_VALUE_RANGE REGISTER="pclath" VALUE="0x0" START_ADDRESS="CODE:0547" LENGTH="0x42" />
        <REGISTER_VALUE_RANGE REGISTER="pclath" VALUE="0x0" START_ADDRESS="CODE:0568" LENGTH="0xE" />
        <REGISTER_VALUE_RANGE REGISTER="pclath" VALUE="0x0" START_ADDRESS="CODE:056F" LENGTH="0x42" />
        <REGISTER_VALUE_RANGE REGISTER="pclath" VALUE="0x0" START_ADDRESS="CODE:0590" LENGTH="0xE" />
        <REGISTER_VALUE_RANGE REGISTER="pclath" VALUE="0x0" START_ADDRESS="CODE:0597" LENGTH="0x4E" />
        <REGISTER_VALUE_RANGE REGISTER="pclath" VALUE="0x0" START_ADDRESS="CODE:05BE" LENGTH="0xE" />
        <REGISTER_VALUE_RANGE REGISTER="pclath" VALUE="0x0" START_ADDRESS="CODE:05C5" LENGTH="0x6A" />
        <REGISTER_VALUE_RANGE REGISTER="pclath" VALUE="0x0" START_ADDRESS="CODE:05FA" LENGTH="0xE" />
        <REGISTER_VALUE_RANGE REGISTER="pclath" VALUE="0x0" START_ADDRESS="CODE:0601" LENGTH="0x70" />
        <REGISTER_VALUE_RANGE REGISTER="pclath" VALUE="0x0" START_ADDRESS="CODE:0639" LENGTH="0xE" />
        <REGISTER_VALUE_RANGE REGISTER="pclath" VALUE="0x0" START_ADDRESS="CODE:0640" LENGTH="0x92" />
        <REGISTER_VALUE_RANGE REGISTER="pclath" VALUE="0x0" START_ADDRESS="CODE:0689" LENGTH="0xE" />
        <REGISTER_VALUE_RANGE REGISTER="pclath" VALUE="0x0" START_ADDRESS="CODE:0690" LENGTH="0x2E0" />
        <REGISTER_VALUE_RANGE REGISTER="pclath" VALUE="0x8" START_ADDRESS="CODE:0800" LENGTH="0xE" />
        <REGISTER_VALUE_RANGE REGISTER="pclath" VALUE="0x0" START_ADDRESS="CODE:0807" LENGTH="0xCE" />
        <REGISTER_VALUE_RANGE REGISTER="pclath" VALUE="0x8" START_ADDRESS="CODE:086E" LENGTH="0xE" />
        <REGISTER_VALUE_RANGE REGISTER="pclath" VALUE="0x0" START_ADDRESS="CODE:0875" LENGTH="0x86" />
        <REGISTER_VALUE_RANGE REGISTER="pclath" VALUE="0x8" START_ADDRESS="CODE:08B8" LENGTH="0xE" />
        <REGISTER_VALUE_RANGE REGISTER="pclath" VALUE="0x0" START_ADDRESS="CODE:08BF" LENGTH="0x15E" />
        <REGISTER_VALUE_RANGE REGISTER="pclath" VALUE="0x8" START_ADDRESS="CODE:096E" LENGTH="0xE" />
        <REGISTER_VALUE_RANGE REGISTER="pclath" VALUE="0x0" START_ADDRESS="CODE:0975" LENGTH="0x1C6" />
        <REGISTER_VALUE_RANGE REGISTER="pclath" VALUE="0x8" START_ADDRESS="CODE:0A58" LENGTH="0x1A" />
        <REGISTER_VALUE_RANGE REGISTER="pclath" VALUE="0x8" START_ADDRESS="CODE:0A65" LENGTH="0x6" />
        <REGISTER_VALUE_RANGE REGISTER="pclath" VALUE="0x8" START_ADDRESS="CODE:0A68" LENGTH="0x4" />
        <REGISTER_VALUE_RANGE REGISTER="pclath" VALUE="0x8" START_ADDRESS="CODE:0A6A" LENGTH="0xB2C" />
        <REGISTER_VALUE_RANGE REGISTER="pclath" VALUE="0x0" START_ADDRESS="DATA:0000" LENGTH="0x400" />
    </REGISTER_VALUES>
    <CODE>
        <CODE_BLOCK START="CODE:0000" END="CODE:0001" />
        <CODE_BLOCK START="CODE:0004" END="CODE:020E" />
        <CODE_BLOCK START="CODE:039D" END="CODE:03A5" />
        <CODE_BLOCK START="CODE:04CD" END="CODE:04D5" />
        <CODE_BLOCK START="CODE:0540" END="CODE:0548" />
        <CODE_BLOCK START="CODE:0568" END="CODE:0570" />
        <CODE_BLOCK START="CODE:0590" END="CODE:0598" />
        <CODE_BLOCK START="CODE:05BE" END="CODE:05C6" />
        <CODE_BLOCK START="CODE:05FA" END="CODE:0602" />
        <CODE_BLOCK START="CODE:0639" END="CODE:0641" />
        <CODE_BLOCK START="CODE:0689" END="CODE:0691" />
        <CODE_BLOCK START="CODE:0800" END="CODE:0808" />
        <CODE_BLOCK START="CODE:086E" END="CODE:0876" />
        <CODE_BLOCK START="CODE:08B8" END="CODE:08C0" />
        <CODE_BLOCK START="CODE:096E" END="CODE:0976" />
        <CODE_BLOCK START="CODE:0A58" END="CODE:0A6A" />
    </CODE>
    <DATA>
        <DEFINED_DATA ADDRESS="DATA:0000" DATATYPE="word" SIZE="0x2">
            <TYPEINFO_CMT>BANK0:INDF</TYPEINFO_CMT>
        </DEFINED_DATA>
        <DEFINED_DATA ADDRESS="DATA:0001" DATATYPE="word" SIZE="0x2">
            <TYPEINFO_CMT>BANK0:TMR0</TYPEINFO_CMT>
        </DEFINED_DATA>
        <DEFINED_DATA ADDRESS="DATA:0002" DATATYPE="word" SIZE="0x2">
            <TYPEINFO_CMT>BANK0:PCL</TYPEINFO_CMT>
        </DEFINED_DATA>
        <DEFINED_DATA ADDRESS="DATA:0003" DATATYPE="word" SIZE="0x2">
            <TYPEINFO_CMT>BANK0:STATUS</TYPEINFO_CMT>
        </DEFINED_DATA>
        <DEFINED_DATA ADDRESS="DATA:0004" DATATYPE="word" SIZE="0x2">
            <TYPEINFO_CMT>BANK0:FSR</TYPEINFO_CMT>
        </DEFINED_DATA>
        <DEFINED_DATA ADDRESS="DATA:0005" DATATYPE="word" SIZE="0x2">
            <TYPEINFO_CMT>BANK0:PORTA</TYPEINFO_CMT>
        </DEFINED_DATA>
        <DEFINED_DATA ADDRESS="DATA:0006" DATATYPE="word" SIZE="0x2">
            <TYPEINFO_CMT>BANK0:PORTB</TYPEINFO_CMT>
        </DEFINED_DATA>
        <DEFINED_DATA ADDRESS="DATA:0007" DATATYPE="word" SIZE="0x2">
            <TYPEINFO_CMT>BANK0:PORTC</TYPEINFO_CMT>
        </DEFINED_DATA>
        <DEFINED_DATA ADDRESS="DATA:0008" DATATYPE="word" SIZE="0x2">
            <TYPEINFO_CMT>BANK0:RESERVED0008</TYPEINFO_CMT>
        </DEFINED_DATA>
        <DEFINED_DATA ADDRESS="DATA:0009" DATATYPE="word" SIZE="0x2">
            <TYPEINFO_CMT>BANK0:RESERVED0009</TYPEINFO_CMT>
        </DEFINED_DATA>
        <DEFINED_DATA ADDRESS="DATA:000A" DATATYPE="word" SIZE="0x2">
            <TYPEINFO_CMT>BANK0:PCLATH</TYPEINFO_CMT>
        </DEFINED_DATA>
        <DEFINED_DATA ADDRESS="DATA:000B" DATATYPE="word" SIZE="0x2">
            <TYPEINFO_CMT>BANK0:INTCON</TYPEINFO_CMT>
        </DEFINED_DATA>
        <DEFINED_DATA ADDRESS="DATA:000C" DATATYPE="word" SIZE="0x2">
            <TYPEINFO_CMT>BANK0:PIR1</TYPEINFO_CMT>
        </DEFINED_DATA>
        <DEFINED_DATA ADDRESS="DATA:000D" DATATYPE="word" SIZE="0x2">
            <TYPEINFO_CMT>BANK0:PIR2</TYPEINFO_CMT>
        </DEFINED_DATA>
        <DEFINED_DATA ADDRESS="DATA:000E" DATATYPE="word" SIZE="0x2">
            <TYPEINFO_CMT>BANK0:TMR1L</TYPEINFO_CMT>
        </DEFINED_DATA>
        <DEFINED_DATA ADDRESS="DATA:000F" DATATYPE="word" SIZE="0x2">
            <TYPEINFO_CMT>BANK0:TMR1H</TYPEINFO_CMT>
        </DEFINED_DATA>
        <DEFINED_DATA ADDRESS="DATA:0010" DATATYPE="word" SIZE="0x2">
            <TYPEINFO_CMT>BANK0:T1CON</TYPEINFO_CMT>
        </DEFINED_DATA>
        <DEFINED_DATA ADDRESS="DATA:0011" DATATYPE="word" SIZE="0x2">
            <TYPEINFO_CMT>BANK0:TMR2</TYPEINFO_CMT>
        </DEFINED_DATA>
        <DEFINED_DATA ADDRESS="DATA:0012" DATATYPE="word" SIZE="0x2">
            <TYPEINFO_CMT>BANK0:T2CON</TYPEINFO_CMT>
        </DEFINED_DATA>
        <DEFINED_DATA ADDRESS="DATA:0013" DATATYPE="word" SIZE="0x2">
            <TYPEINFO_CMT>BANK0:SSPBUF</TYPEINFO_CMT>
        </DEFINED_DATA>
        <DEFINED_DATA ADDRESS="DATA:0014" DATATYPE="word" SIZE="0x2">
            <TYPEINFO_CMT>BANK0:SSPCON</TYPEINFO_CMT>
        </DEFINED_DATA>
        <DEFINED_DATA ADDRESS="DATA:0015" DATATYPE="word" SIZE="0x2">
            <TYPEINFO_CMT>BANK0:CCPR1L</TYPEINFO_CMT>
        </DEFINED_DATA>
        <DEFINED_DATA ADDRESS="DATA:0016" DATATYPE="word" SIZE="0x2">
            <TYPEINFO_CMT>BANK0:CCPR1H</TYPEINFO_CMT>
        </DEFINED_DATA>
        <DEFINED_DATA ADDRESS="DATA:0017" DATATYPE="word" SIZE="0x2">
            <TYPEINFO_CMT>BANK0:CCP1CON</TYPEINFO_CMT>
        </DEFINED_DATA>
        <DEFINED_DATA ADDRESS="DATA:0018" DATATYPE="word" SIZE="0x2">
            <TYPEINFO_CMT>BANK0:RCSTA</TYPEINFO_CMT>
        </DEFINED_DATA>
        <DEFINED_DATA ADDRESS="DATA:0019" DATATYPE="word" SIZE="0x2">
            <TYPEINFO_CMT>BANK0:TXREG</TYPEINFO_CMT>
        </DEFINED_DATA>
        <DEFINED_DATA ADDRESS="DATA:001A" DATATYPE="word" SIZE="0x2">
            <TYPEINFO_CMT>BANK0:RCREG</TYPEINFO_CMT>
        </DEFINED_DATA>
        <DEFINED_DATA ADDRESS="DATA:001B" DATATYPE="word" SIZE="0x2">
            <TYPEINFO_CMT>BANK0:CCPR2L</TYPEINFO_CMT>
        </DEFINED_DATA>
        <DEFINED_DATA ADDRESS="DATA:001C" DATATYPE="word" SIZE="0x2">
            <TYPEINFO_CMT>BANK0:CCPR2H</TYPEINFO_CMT>
        </DEFINED_DATA>
        <DEFINED_DATA ADDRESS="DATA:001D" DATATYPE="word" SIZE="0x2">
            <TYPEINFO_CMT>BANK0:CCP2CON</TYPEINFO_CMT>
        </DEFINED_DATA>
        <DEFINED_DATA ADDRESS="DATA:001E" DATATYPE="word" SIZE="0x2">
            <TYPEINFO_CMT>BANK0:RESERVED001E</TYPEINFO_CMT>
        </DEFINED_DATA>
        <DEFINED_DATA ADDRESS="DATA:001F" DATATYPE="word" SIZE="0x2">
            <TYPEINFO_CMT>BANK0:RESERVED001F</TYPEINFO_CMT>
        </DEFINED_DATA>
        <DEFINED_DATA ADDRESS="DATA:0020" DATATYPE="word" SIZE="0x2">
            <TYPEINFO_CMT>byte_DATA_20</TYPEINFO_CMT>
        </DEFINED_DATA>
        <DEFINED_DATA ADDRESS="DATA:0021" DATATYPE="word" SIZE="0x2">
            <TYPEINFO_CMT>byte_DATA_21</TYPEINFO_CMT>
        </DEFINED_DATA>
        <DEFINED_DATA ADDRESS="DATA:0022" DATATYPE="word" SIZE="0x2">
            <TYPEINFO_CMT>byte_DATA_22</TYPEINFO_CMT>
        </DEFINED_DATA>
        <DEFINED_DATA ADDRESS="DATA:0023" DATATYPE="word" SIZE="0x2">
            <TYPEINFO_CMT>byte_DATA_23</TYPEINFO_CMT>
        </DEFINED_DATA>
        <DEFINED_DATA ADDRESS="DATA:0024" DATATYPE="word[2]" SIZE="0x4">
            <TYPEINFO_CMT>byte_DATA_24</TYPEINFO_CMT>
        </DEFINED_DATA>
        <DEFINED_DATA ADDRESS="DATA:0026" DATATYPE="word" SIZE="0x2">
            <TYPEINFO_CMT>byte_DATA_26</TYPEINFO_CMT>
        </DEFINED_DATA>
        <DEFINED_DATA ADDRESS="DATA:0027" DATATYPE="word" SIZE="0x2">
            <TYPEINFO_CMT>byte_DATA_27</TYPEINFO_CMT>
        </DEFINED_DATA>
        <DEFINED_DATA ADDRESS="DATA:0028" DATATYPE="word[4]" SIZE="0x8">
            <TYPEINFO_CMT>byte_DATA_28</TYPEINFO_CMT>
        </DEFINED_DATA>
        <DEFINED_DATA ADDRESS="DATA:002C" DATATYPE="word" SIZE="0x2">
            <TYPEINFO_CMT>byte_DATA_2C</TYPEINFO_CMT>
        </DEFINED_DATA>
        <DEFINED_DATA ADDRESS="DATA:002D" DATATYPE="word[3]" SIZE="0x6" />
        <DEFINED_DATA ADDRESS="DATA:0030" DATATYPE="word" SIZE="0x2">
            <TYPEINFO_CMT>byte_DATA_30</TYPEINFO_CMT>
        </DEFINED_DATA>
        <DEFINED_DATA ADDRESS="DATA:0031" DATATYPE="word" SIZE="0x2">
            <TYPEINFO_CMT>byte_DATA_31</TYPEINFO_CMT>
        </DEFINED_DATA>
        <DEFINED_DATA ADDRESS="DATA:0032" DATATYPE="word" SIZE="0x2">
            <TYPEINFO_CMT>byte_DATA_32</TYPEINFO_CMT>
        </DEFINED_DATA>
        <DEFINED_DATA ADDRESS="DATA:0033" DATATYPE="word" SIZE="0x2">
            <TYPEINFO_CMT>byte_DATA_33</TYPEINFO_CMT>
        </DEFINED_DATA>
        <DEFINED_DATA ADDRESS="DATA:0034" DATATYPE="word" SIZE="0x2">
            <TYPEINFO_CMT>byte_DATA_34</TYPEINFO_CMT>
        </DEFINED_DATA>
        <DEFINED_DATA ADDRESS="DATA:0035" DATATYPE="word" SIZE="0x2">
            <TYPEINFO_CMT>byte_DATA_35</TYPEINFO_CMT>
        </DEFINED_DATA>
        <DEFINED_DATA ADDRESS="DATA:0036" DATATYPE="word" SIZE="0x2">
            <TYPEINFO_CMT>byte_DATA_36</TYPEINFO_CMT>
        </DEFINED_DATA>
        <DEFINED_DATA ADDRESS="DATA:0037" DATATYPE="word" SIZE="0x2">
            <TYPEINFO_CMT>byte_DATA_37</TYPEINFO_CMT>
        </DEFINED_DATA>
        <DEFINED_DATA ADDRESS="DATA:0038" DATATYPE="word" SIZE="0x2">
            <TYPEINFO_CMT>byte_DATA_38</TYPEINFO_CMT>
        </DEFINED_DATA>
        <DEFINED_DATA ADDRESS="DATA:0039" DATATYPE="word" SIZE="0x2">
            <TYPEINFO_CMT>byte_DATA_39</TYPEINFO_CMT>
        </DEFINED_DATA>
        <DEFINED_DATA ADDRESS="DATA:003A" DATATYPE="word" SIZE="0x2">
            <TYPEINFO_CMT>byte_DATA_3A</TYPEINFO_CMT>
        </DEFINED_DATA>
        <DEFINED_DATA ADDRESS="DATA:003B" DATATYPE="word" SIZE="0x2">
            <TYPEINFO_CMT>byte_DATA_3B</TYPEINFO_CMT>
        </DEFINED_DATA>
        <DEFINED_DATA ADDRESS="DATA:003C" DATATYPE="word" SIZE="0x2">
            <TYPEINFO_CMT>byte_DATA_3C</TYPEINFO_CMT>
        </DEFINED_DATA>
        <DEFINED_DATA ADDRESS="DATA:003D" DATATYPE="word" SIZE="0x2">
            <TYPEINFO_CMT>byte_DATA_3D</TYPEINFO_CMT>
        </DEFINED_DATA>
        <DEFINED_DATA ADDRESS="DATA:003E" DATATYPE="word" SIZE="0x2">
            <TYPEINFO_CMT>byte_DATA_3E</TYPEINFO_CMT>
        </DEFINED_DATA>
        <DEFINED_DATA ADDRESS="DATA:003F" DATATYPE="word" SIZE="0x2">
            <TYPEINFO_CMT>byte_DATA_3F</TYPEINFO_CMT>
        </DEFINED_DATA>
        <DEFINED_DATA ADDRESS="DATA:0040" DATATYPE="word[2]" SIZE="0x4" />
        <DEFINED_DATA ADDRESS="DATA:0042" DATATYPE="word" SIZE="0x2">
            <TYPEINFO_CMT>byte_DATA_42</TYPEINFO_CMT>
        </DEFINED_DATA>
        <DEFINED_DATA ADDRESS="DATA:0043" DATATYPE="word[14]" SIZE="0x1C" />
        <DEFINED_DATA ADDRESS="DATA:0051" DATATYPE="word" SIZE="0x2">
            <TYPEINFO_CMT>byte_DATA_51</TYPEINFO_CMT>
        </DEFINED_DATA>
        <DEFINED_DATA ADDRESS="DATA:0052" DATATYPE="word" SIZE="0x2">
            <TYPEINFO_CMT>byte_DATA_52</TYPEINFO_CMT>
        </DEFINED_DATA>
        <DEFINED_DATA ADDRESS="DATA:0053" DATATYPE="word" SIZE="0x2">
            <TYPEINFO_CMT>byte_DATA_53</TYPEINFO_CMT>
        </DEFINED_DATA>
        <DEFINED_DATA ADDRESS="DATA:0054" DATATYPE="word" SIZE="0x2">
            <TYPEINFO_CMT>byte_DATA_54</TYPEINFO_CMT>
        </DEFINED_DATA>
        <DEFINED_DATA ADDRESS="DATA:0055" DATATYPE="word" SIZE="0x2">
            <TYPEINFO_CMT>byte_DATA_55</TYPEINFO_CMT>
        </DEFINED_DATA>
        <DEFINED_DATA ADDRESS="DATA:0056" DATATYPE="word" SIZE="0x2">
            <TYPEINFO_CMT>byte_DATA_56</TYPEINFO_CMT>
        </DEFINED_DATA>
        <DEFINED_DATA ADDRESS="DATA:0057" DATATYPE="word" SIZE="0x2">
            <TYPEINFO_CMT>byte_DATA_57</TYPEINFO_CMT>
        </DEFINED_DATA>
        <DEFINED_DATA ADDRESS="DATA:0058" DATATYPE="word[11]" SIZE="0x16" />
        <DEFINED_DATA ADDRESS="DATA:0063" DATATYPE="word" SIZE="0x2">
            <TYPEINFO_CMT>byte_DATA_63</TYPEINFO_CMT>
        </DEFINED_DATA>
        <DEFINED_DATA ADDRESS="DATA:0064" DATATYPE="word" SIZE="0x2">
            <TYPEINFO_CMT>byte_DATA_64</TYPEINFO_CMT>
        </DEFINED_DATA>
        <DEFINED_DATA ADDRESS="DATA:0065" DATATYPE="word" SIZE="0x2">
            <TYPEINFO_CMT>byte_DATA_65</TYPEINFO_CMT>
        </DEFINED_DATA>
        <DEFINED_DATA ADDRESS="DATA:0066" DATATYPE="word" SIZE="0x2">
            <TYPEINFO_CMT>byte_DATA_66</TYPEINFO_CMT>
        </DEFINED_DATA>
        <DEFINED_DATA ADDRESS="DATA:0067" DATATYPE="word" SIZE="0x2">
            <TYPEINFO_CMT>byte_DATA_67</TYPEINFO_CMT>
        </DEFINED_DATA>
        <DEFINED_DATA ADDRESS="DATA:0068" DATATYPE="word" SIZE="0x2">
            <TYPEINFO_CMT>byte_DATA_68</TYPEINFO_CMT>
        </DEFINED_DATA>
        <DEFINED_DATA ADDRESS="DATA:0069" DATATYPE="word" SIZE="0x2">
            <TYPEINFO_CMT>byte_DATA_69</TYPEINFO_CMT>
        </DEFINED_DATA>
        <DEFINED_DATA ADDRESS="DATA:006A" DATATYPE="word" SIZE="0x2">
            <TYPEINFO_CMT>byte_DATA_6A</TYPEINFO_CMT>
        </DEFINED_DATA>
        <DEFINED_DATA ADDRESS="DATA:006B" DATATYPE="word" SIZE="0x2">
            <TYPEINFO_CMT>byte_DATA_6B</TYPEINFO_CMT>
        </DEFINED_DATA>
        <DEFINED_DATA ADDRESS="DATA:006C" DATATYPE="word" SIZE="0x2">
            <TYPEINFO_CMT>byte_DATA_6C</TYPEINFO_CMT>
        </DEFINED_DATA>
        <DEFINED_DATA ADDRESS="DATA:006D" DATATYPE="word" SIZE="0x2">
            <TYPEINFO_CMT>byte_DATA_6D</TYPEINFO_CMT>
        </DEFINED_DATA>
        <DEFINED_DATA ADDRESS="DATA:006E" DATATYPE="word" SIZE="0x2">
            <TYPEINFO_CMT>byte_DATA_6E</TYPEINFO_CMT>
        </DEFINED_DATA>
        <DEFINED_DATA ADDRESS="DATA:006F" DATATYPE="word" SIZE="0x2">
            <TYPEINFO_CMT>byte_DATA_6F</TYPEINFO_CMT>
        </DEFINED_DATA>
        <DEFINED_DATA ADDRESS="DATA:0070" DATATYPE="word" SIZE="0x2">
            <TYPEINFO_CMT>byte_DATA_70</TYPEINFO_CMT>
        </DEFINED_DATA>
        <DEFINED_DATA ADDRESS="DATA:0071" DATATYPE="word" SIZE="0x2">
            <TYPEINFO_CMT>byte_DATA_71</TYPEINFO_CMT>
        </DEFINED_DATA>
        <DEFINED_DATA ADDRESS="DATA:0072" DATATYPE="word" SIZE="0x2">
            <TYPEINFO_CMT>byte_DATA_72</TYPEINFO_CMT>
        </DEFINED_DATA>
        <DEFINED_DATA ADDRESS="DATA:0073" DATATYPE="word" SIZE="0x2">
            <TYPEINFO_CMT>byte_DATA_73</TYPEINFO_CMT>
        </DEFINED_DATA>
        <DEFINED_DATA ADDRESS="DATA:0074" DATATYPE="word[12]" SIZE="0x18" />
        <DEFINED_DATA ADDRESS="DATA:0080" DATATYPE="word" SIZE="0x2">
            <TYPEINFO_CMT>BANK1:INDF</TYPEINFO_CMT>
        </DEFINED_DATA>
        <DEFINED_DATA ADDRESS="DATA:0081" DATATYPE="word" SIZE="0x2">
            <TYPEINFO_CMT>BANK1:OPTION</TYPEINFO_CMT>
        </DEFINED_DATA>
        <DEFINED_DATA ADDRESS="DATA:0082" DATATYPE="word" SIZE="0x2">
            <TYPEINFO_CMT>BANK1:PCL</TYPEINFO_CMT>
        </DEFINED_DATA>
        <DEFINED_DATA ADDRESS="DATA:0083" DATATYPE="word" SIZE="0x2">
            <TYPEINFO_CMT>BANK1:STATUS</TYPEINFO_CMT>
        </DEFINED_DATA>
        <DEFINED_DATA ADDRESS="DATA:0084" DATATYPE="word" SIZE="0x2">
            <TYPEINFO_CMT>BANK1:FSR</TYPEINFO_CMT>
        </DEFINED_DATA>
        <DEFINED_DATA ADDRESS="DATA:0085" DATATYPE="word" SIZE="0x2">
            <TYPEINFO_CMT>BANK1:TRISA</TYPEINFO_CMT>
        </DEFINED_DATA>
        <DEFINED_DATA ADDRESS="DATA:0086" DATATYPE="word" SIZE="0x2">
            <TYPEINFO_CMT>BANK1:TRISB</TYPEINFO_CMT>
        </DEFINED_DATA>
        <DEFINED_DATA ADDRESS="DATA:0087" DATATYPE="word" SIZE="0x2">
            <TYPEINFO_CMT>BANK1:TRISC</TYPEINFO_CMT>
        </DEFINED_DATA>
        <DEFINED_DATA ADDRESS="DATA:0088" DATATYPE="word" SIZE="0x2">
            <TYPEINFO_CMT>BANK1:RESERVED0088</TYPEINFO_CMT>
        </DEFINED_DATA>
        <DEFINED_DATA ADDRESS="DATA:0089" DATATYPE="word" SIZE="0x2">
            <TYPEINFO_CMT>BANK1:RESERVED0089</TYPEINFO_CMT>
        </DEFINED_DATA>
        <DEFINED_DATA ADDRESS="DATA:008A" DATATYPE="word" SIZE="0x2">
            <TYPEINFO_CMT>BANK1:PCLATH</TYPEINFO_CMT>
        </DEFINED_DATA>
        <DEFINED_DATA ADDRESS="DATA:008B" DATATYPE="word" SIZE="0x2">
            <TYPEINFO_CMT>BANK1:INTCON</TYPEINFO_CMT>
        </DEFINED_DATA>
        <DEFINED_DATA ADDRESS="DATA:008C" DATATYPE="word" SIZE="0x2">
            <TYPEINFO_CMT>BANK1:PIE1</TYPEINFO_CMT>
        </DEFINED_DATA>
        <DEFINED_DATA ADDRESS="DATA:008D" DATATYPE="word" SIZE="0x2">
            <TYPEINFO_CMT>BANK1:PIE2</TYPEINFO_CMT>
        </DEFINED_DATA>
        <DEFINED_DATA ADDRESS="DATA:008E" DATATYPE="word" SIZE="0x2">
            <TYPEINFO_CMT>BANK1:PCON</TYPEINFO_CMT>
        </DEFINED_DATA>
        <DEFINED_DATA ADDRESS="DATA:008F" DATATYPE="word" SIZE="0x2">
            <TYPEINFO_CMT>BANK1:RESERVED000F</TYPEINFO_CMT>
        </DEFINED_DATA>
        <DEFINED_DATA ADDRESS="DATA:0090" DATATYPE="word" SIZE="0x2">
            <TYPEINFO_CMT>BANK1:RESERVED0090</TYPEINFO_CMT>
        </DEFINED_DATA>
        <DEFINED_DATA ADDRESS="DATA:0091" DATATYPE="word" SIZE="0x2">
            <TYPEINFO_CMT>BANK1:RESERVED0091</TYPEINFO_CMT>
        </DEFINED_DATA>
        <DEFINED_DATA ADDRESS="DATA:0092" DATATYPE="word" SIZE="0x2">
            <TYPEINFO_CMT>BANK1:PR2</TYPEINFO_CMT>
        </DEFINED_DATA>
        <DEFINED_DATA ADDRESS="DATA:0093" DATATYPE="word" SIZE="0x2">
            <TYPEINFO_CMT>BANK1:SSPADD</TYPEINFO_CMT>
        </DEFINED_DATA>
        <DEFINED_DATA ADDRESS="DATA:0094" DATATYPE="word" SIZE="0x2">
            <TYPEINFO_CMT>BANK1:SSPSTAT</TYPEINFO_CMT>
        </DEFINED_DATA>
        <DEFINED_DATA ADDRESS="DATA:0095" DATATYPE="word" SIZE="0x2">
            <TYPEINFO_CMT>BANK1:RESERVED0095</TYPEINFO_CMT>
        </DEFINED_DATA>
        <DEFINED_DATA ADDRESS="DATA:0096" DATATYPE="word" SIZE="0x2">
            <TYPEINFO_CMT>BANK1:RESERVED0096</TYPEINFO_CMT>
        </DEFINED_DATA>
        <DEFINED_DATA ADDRESS="DATA:0097" DATATYPE="word" SIZE="0x2">
            <TYPEINFO_CMT>BANK1:RESERVED0097</TYPEINFO_CMT>
        </DEFINED_DATA>
        <DEFINED_DATA ADDRESS="DATA:0098" DATATYPE="word" SIZE="0x2">
            <TYPEINFO_CMT>BANK1:TXSTA</TYPEINFO_CMT>
        </DEFINED_DATA>
        <DEFINED_DATA ADDRESS="DATA:0099" DATATYPE="word" SIZE="0x2">
            <TYPEINFO_CMT>BANK1:SPBRG</TYPEINFO_CMT>
        </DEFINED_DATA>
        <DEFINED_DATA ADDRESS="DATA:009A" DATATYPE="word" SIZE="0x2">
            <TYPEINFO_CMT>BANK1:RESERVED009A</TYPEINFO_CMT>
        </DEFINED_DATA>
        <DEFINED_DATA ADDRESS="DATA:009B" DATATYPE="word" SIZE="0x2">
            <TYPEINFO_CMT>BANK1:RESERVED009B</TYPEINFO_CMT>
        </DEFINED_DATA>
        <DEFINED_DATA ADDRESS="DATA:009C" DATATYPE="word" SIZE="0x2">
            <TYPEINFO_CMT>BANK1:RESERVED009C</TYPEINFO_CMT>
        </DEFINED_DATA>
        <DEFINED_DATA ADDRESS="DATA:009D" DATATYPE="word" SIZE="0x2">
            <TYPEINFO_CMT>BANK1:RESERVED009D</TYPEINFO_CMT>
        </DEFINED_DATA>
        <DEFINED_DATA ADDRESS="DATA:009E" DATATYPE="word" SIZE="0x2">
            <TYPEINFO_CMT>BANK1:RESERVED009E</TYPEINFO_CMT>
        </DEFINED_DATA>
        <DEFINED_DATA ADDRESS="DATA:009F" DATATYPE="word" SIZE="0x2">
            <TYPEINFO_CMT>BANK1:RESERVED009F</TYPEINFO_CMT>
        </DEFINED_DATA>
        <DEFINED_DATA ADDRESS="DATA:00A0" DATATYPE="word[4]" SIZE="0x8" />
        <DEFINED_DATA ADDRESS="DATA:00A4" DATATYPE="word" SIZE="0x2">
            <TYPEINFO_CMT>byte_DATA_A4</TYPEINFO_CMT>
        </DEFINED_DATA>
        <DEFINED_DATA ADDRESS="DATA:00A5" DATATYPE="word[3]" SIZE="0x6" />
        <DEFINED_DATA ADDRESS="DATA:00A8" DATATYPE="word" SIZE="0x2">
            <TYPEINFO_CMT>byte_DATA_A8</TYPEINFO_CMT>
        </DEFINED_DATA>
        <DEFINED_DATA ADDRESS="DATA:00A9" DATATYPE="word[343]" SIZE="0x2AE" />
    </DATA>
    <COMMENTS>
        <COMMENT ADDRESS="CODE:004B" TYPE="repeatable">Jump to read handler </COMMENT>
        <COMMENT ADDRESS="CODE:004D" TYPE="repeatable">Read command 0x1 </COMMENT>
        <COMMENT ADDRESS="CODE:004E" TYPE="repeatable">Read command 0x2 </COMMENT>
        <COMMENT ADDRESS="CODE:004F" TYPE="repeatable">Read command 0x3 </COMMENT>
        <COMMENT ADDRESS="CODE:0050" TYPE="repeatable">Read command 0x4 </COMMENT>
        <COMMENT ADDRESS="CODE:0051" TYPE="repeatable">Read command 0x5 </COMMENT>
        <COMMENT ADDRESS="CODE:0052" TYPE="repeatable">Read command 0x6 </COMMENT>
        <COMMENT ADDRESS="CODE:0053" TYPE="repeatable">Read command 0x7 </COMMENT>
        <COMMENT ADDRESS="CODE:0054" TYPE="repeatable">Read command 0x8 </COMMENT>
        <COMMENT ADDRESS="CODE:0055" TYPE="repeatable">Read command 0x9 </COMMENT>
        <COMMENT ADDRESS="CODE:0056" TYPE="repeatable">Read command 0xA </COMMENT>
        <COMMENT ADDRESS="CODE:0057" TYPE="repeatable">Read command 0xB </COMMENT>
        <COMMENT ADDRESS="CODE:0058" TYPE="repeatable">Read command 0xC </COMMENT>
        <COMMENT ADDRESS="CODE:0059" TYPE="repeatable">Read command 0xD </COMMENT>
        <COMMENT ADDRESS="CODE:005A" TYPE="repeatable">Read command 0xE </COMMENT>
        <COMMENT ADDRESS="CODE:005B" TYPE="repeatable">Read command 0xF </COMMENT>
        <COMMENT ADDRESS="CODE:005C" TYPE="repeatable">Read command 0x10 </COMMENT>
        <COMMENT ADDRESS="CODE:005D" TYPE="repeatable">Read command 0x11 </COMMENT>
        <COMMENT ADDRESS="CODE:005E" TYPE="repeatable">Read command 0x12 </COMMENT>
        <COMMENT ADDRESS="CODE:005F" TYPE="repeatable">Read command 0x13 </COMMENT>
        <COMMENT ADDRESS="CODE:0060" TYPE="repeatable">Read command 0x14 </COMMENT>
        <COMMENT ADDRESS="CODE:0061" TYPE="repeatable">Read command 0x15 </COMMENT>
        <COMMENT ADDRESS="CODE:0062" TYPE="repeatable">Read command 0x16 </COMMENT>
        <COMMENT ADDRESS="CODE:0063" TYPE="repeatable">Read command 0x17 </COMMENT>
        <COMMENT ADDRESS="CODE:0064" TYPE="repeatable">Read command 0x18 </COMMENT>
        <COMMENT ADDRESS="CODE:0065" TYPE="repeatable">Read command 0x19 </COMMENT>
        <COMMENT ADDRESS="CODE:0067" TYPE="repeatable">Version B2A </COMMENT>
        <COMMENT ADDRESS="CODE:00D7" TYPE="repeatable">Jump to write handler </COMMENT>
        <COMMENT ADDRESS="CODE:00D9" TYPE="repeatable">Write command 0x1 </COMMENT>
        <COMMENT ADDRESS="CODE:00DA" TYPE="repeatable">Write command 0x2 </COMMENT>
        <COMMENT ADDRESS="CODE:00DB" TYPE="repeatable">Write command 0x3 </COMMENT>
        <COMMENT ADDRESS="CODE:00DC" TYPE="repeatable">Write command 0x4 </COMMENT>
        <COMMENT ADDRESS="CODE:00DD" TYPE="repeatable">Write command 0x5 </COMMENT>
        <COMMENT ADDRESS="CODE:00DE" TYPE="repeatable">Write command 0x6 </COMMENT>
        <COMMENT ADDRESS="CODE:00DF" TYPE="repeatable">Write command 0x7 </COMMENT>
        <COMMENT ADDRESS="CODE:00E0" TYPE="repeatable">Write command 0x8 </COMMENT>
        <COMMENT ADDRESS="CODE:00E1" TYPE="repeatable">Write command 0x9 </COMMENT>
        <COMMENT ADDRESS="CODE:00E2" TYPE="repeatable">Write command 0xA </COMMENT>
        <COMMENT ADDRESS="CODE:00E3" TYPE="repeatable">Write command 0xB </COMMENT>
        <COMMENT ADDRESS="CODE:00E4" TYPE="repeatable">Write command 0xC </COMMENT>
        <COMMENT ADDRESS="CODE:00E5" TYPE="repeatable">Write command 0xD </COMMENT>
        <COMMENT ADDRESS="CODE:00E6" TYPE="repeatable">Write command 0xE </COMMENT>
        <COMMENT ADDRESS="CODE:00E7" TYPE="repeatable">Write command 0xF </COMMENT>
        <COMMENT ADDRESS="CODE:00E8" TYPE="repeatable">Write command 0x10 </COMMENT>
        <COMMENT ADDRESS="CODE:00E9" TYPE="repeatable">Write command 0x11 </COMMENT>
        <COMMENT ADDRESS="CODE:00EA" TYPE="repeatable">Write command 0x12 </COMMENT>
        <COMMENT ADDRESS="CODE:00EB" TYPE="repeatable">Write command 0x13 </COMMENT>
        <COMMENT ADDRESS="CODE:00EC" TYPE="repeatable">Write command 0x14 </COMMENT>
        <COMMENT ADDRESS="CODE:00ED" TYPE="repeatable">Write command 0x15 </COMMENT>
        <COMMENT ADDRESS="CODE:00EE" TYPE="repeatable">Write command 0x16 </COMMENT>
        <COMMENT ADDRESS="CODE:00EF" TYPE="repeatable">Write command 0x17 </COMMENT>
        <COMMENT ADDRESS="CODE:00F0" TYPE="repeatable">Write command 0x18 </COMMENT>
        <COMMENT ADDRESS="CODE:00F1" TYPE="repeatable">Write command 0x19 </COMMENT>
        <COMMENT ADDRESS="CODE:0000" TYPE="pre">; File Name   : D:\Documents\XBOX\SMC\PICProgrammer\dvt3_doom_PIC_descrambled.rev_2byte.bin 
; Format      : Binary file 
; Base Address: 0000h Range: 0000h - 1000h Loaded length: 1000h  </COMMENT>
    </COMMENTS>
    <PROGRAM_ENTRY_POINTS>
        <PROGRAM_ENTRY_POINT ADDRESS="CODE:0000" />
        <PROGRAM_ENTRY_POINT ADDRESS="CODE:0004" />
    </PROGRAM_ENTRY_POINTS>
    <SYMBOL_TABLE>
        <SYMBOL ADDRESS="CODE:0000" NAME="RESET" />
        <SYMBOL ADDRESS="CODE:0004" NAME="ISR" />
        <SYMBOL ADDRESS="CODE:004C" NAME="ISR_SMBus_Reads" />
        <SYMBOL ADDRESS="CODE:00D8" NAME="ISR_SMBus_Writes" />
        <SYMBOL ADDRESS="CODE:016E" NAME="ISR_End" />
        <SYMBOL ADDRESS="DATA:0000" NAME="BANK0:INDF" />
        <SYMBOL ADDRESS="DATA:0001" NAME="BANK0:TMR0" />
        <SYMBOL ADDRESS="DATA:0002" NAME="BANK0:PCL" />
        <SYMBOL ADDRESS="DATA:0003" NAME="BANK0:STATUS" />
        <SYMBOL ADDRESS="DATA:0004" NAME="BANK0:FSR" />
        <SYMBOL ADDRESS="DATA:0005" NAME="BANK0:PORTA" />
        <SYMBOL ADDRESS="DATA:0006" NAME="BANK0:PORTB" />
        <SYMBOL ADDRESS="DATA:0007" NAME="BANK0:PORTC" />
        <SYMBOL ADDRESS="DATA:0008" NAME="BANK0:RESERVED0008" />
        <SYMBOL ADDRESS="DATA:0009" NAME="BANK0:RESERVED0009" />
        <SYMBOL ADDRESS="DATA:000A" NAME="BANK0:PCLATH" />
        <SYMBOL ADDRESS="DATA:000B" NAME="BANK0:INTCON" />
        <SYMBOL ADDRESS="DATA:000C" NAME="BANK0:PIR1" />
        <SYMBOL ADDRESS="DATA:000D" NAME="BANK0:PIR2" />
        <SYMBOL ADDRESS="DATA:000E" NAME="BANK0:TMR1L" />
        <SYMBOL ADDRESS="DATA:000F" NAME="BANK0:TMR1H" />
        <SYMBOL ADDRESS="DATA:0010" NAME="BANK0:T1CON" />
        <SYMBOL ADDRESS="DATA:0011" NAME="BANK0:TMR2" />
        <SYMBOL ADDRESS="DATA:0012" NAME="BANK0:T2CON" />
        <SYMBOL ADDRESS="DATA:0013" NAME="BANK0:SSPBUF" />
        <SYMBOL ADDRESS="DATA:0014" NAME="BANK0:SSPCON" />
        <SYMBOL ADDRESS="DATA:0015" NAME="BANK0:CCPR1L" />
        <SYMBOL ADDRESS="DATA:0016" NAME="BANK0:CCPR1H" />
        <SYMBOL ADDRESS="DATA:0017" NAME="BANK0:CCP1CON" />
        <SYMBOL ADDRESS="DATA:0018" NAME="BANK0:RCSTA" />
        <SYMBOL ADDRESS="DATA:0019" NAME="BANK0:TXREG" />
        <SYMBOL ADDRESS="DATA:001A" NAME="BANK0:RCREG" />
        <SYMBOL ADDRESS="DATA:001B" NAME="BANK0:CCPR2L" />
        <SYMBOL ADDRESS="DATA:001C" NAME="BANK0:CCPR2H" />
        <SYMBOL ADDRESS="DATA:001D" NAME="BANK0:CCP2CON" />
        <SYMBOL ADDRESS="DATA:001E" NAME="BANK0:RESERVED001E" />
        <SYMBOL ADDRESS="DATA:001F" NAME="BANK0:RESERVED001F" />
        <SYMBOL ADDRESS="DATA:0080" NAME="BANK1:INDF" />
        <SYMBOL ADDRESS="DATA:0081" NAME="BANK1:OPTION" />
        <SYMBOL ADDRESS="DATA:0082" NAME="BANK1:PCL" />
        <SYMBOL ADDRESS="DATA:0083" NAME="BANK1:STATUS" />
        <SYMBOL ADDRESS="DATA:0084" NAME="BANK1:FSR" />
        <SYMBOL ADDRESS="DATA:0085" NAME="BANK1:TRISA" />
        <SYMBOL ADDRESS="DATA:0086" NAME="BANK1:TRISB" />
        <SYMBOL ADDRESS="DATA:0087" NAME="BANK1:TRISC" />
        <SYMBOL ADDRESS="DATA:0088" NAME="BANK1:RESERVED0088" />
        <SYMBOL ADDRESS="DATA:0089" NAME="BANK1:RESERVED0089" />
        <SYMBOL ADDRESS="DATA:008A" NAME="BANK1:PCLATH" />
        <SYMBOL ADDRESS="DATA:008B" NAME="BANK1:INTCON" />
        <SYMBOL ADDRESS="DATA:008C" NAME="BANK1:PIE1" />
        <SYMBOL ADDRESS="DATA:008D" NAME="BANK1:PIE2" />
        <SYMBOL ADDRESS="DATA:008E" NAME="BANK1:PCON" />
        <SYMBOL ADDRESS="DATA:008F" NAME="BANK1:RESERVED000F" />
        <SYMBOL ADDRESS="DATA:0090" NAME="BANK1:RESERVED0090" />
        <SYMBOL ADDRESS="DATA:0091" NAME="BANK1:RESERVED0091" />
        <SYMBOL ADDRESS="DATA:0092" NAME="BANK1:PR2" />
        <SYMBOL ADDRESS="DATA:0093" NAME="BANK1:SSPADD" />
        <SYMBOL ADDRESS="DATA:0094" NAME="BANK1:SSPSTAT" />
        <SYMBOL ADDRESS="DATA:0095" NAME="BANK1:RESERVED0095" />
        <SYMBOL ADDRESS="DATA:0096" NAME="BANK1:RESERVED0096" />
        <SYMBOL ADDRESS="DATA:0097" NAME="BANK1:RESERVED0097" />
        <SYMBOL ADDRESS="DATA:0098" NAME="BANK1:TXSTA" />
        <SYMBOL ADDRESS="DATA:0099" NAME="BANK1:SPBRG" />
        <SYMBOL ADDRESS="DATA:009A" NAME="BANK1:RESERVED009A" />
        <SYMBOL ADDRESS="DATA:009B" NAME="BANK1:RESERVED009B" />
        <SYMBOL ADDRESS="DATA:009C" NAME="BANK1:RESERVED009C" />
        <SYMBOL ADDRESS="DATA:009D" NAME="BANK1:RESERVED009D" />
        <SYMBOL ADDRESS="DATA:009E" NAME="BANK1:RESERVED009E" />
        <SYMBOL ADDRESS="DATA:009F" NAME="BANK1:RESERVED009F" />
    </SYMBOL_TABLE>
    <FUNCTIONS>
        <FUNCTION ENTRY_POINT="CODE:0000" NAME="RESET">
            <ADDRESS_RANGE START="CODE:0000" END="CODE:0001" />
            <ADDRESS_RANGE START="CODE:01AE" END="CODE:0205" />
            <REPEATABLE_CMT>Reset Vector</REPEATABLE_CMT>
            <TYPEINFO_CMT>undefined RESET()</TYPEINFO_CMT>
        </FUNCTION>
        <FUNCTION ENTRY_POINT="CODE:0004" NAME="ISR">
            <ADDRESS_RANGE START="CODE:0004" END="CODE:004B" />
            <ADDRESS_RANGE START="CODE:00B4" END="CODE:00D7" />
            <ADDRESS_RANGE START="CODE:016E" END="CODE:0178" />
            <REPEATABLE_CMT>Interrupt Vector</REPEATABLE_CMT>
            <TYPEINFO_CMT>undefined ISR()</TYPEINFO_CMT>
        </FUNCTION>
        <FUNCTION ENTRY_POINT="CODE:004C" NAME="ISR_SMBus_Reads">
            <ADDRESS_RANGE START="CODE:004C" END="CODE:00B3" />
            <REPEATABLE_CMT>Read command 0x0</REPEATABLE_CMT>
            <TYPEINFO_CMT>undefined ISR_SMBus_Reads()</TYPEINFO_CMT>
        </FUNCTION>
        <FUNCTION ENTRY_POINT="CODE:00D8" NAME="ISR_SMBus_Writes">
            <ADDRESS_RANGE START="CODE:00D8" END="CODE:016D" />
            <REPEATABLE_CMT>Write command 0x0</REPEATABLE_CMT>
            <TYPEINFO_CMT>undefined ISR_SMBus_Writes()</TYPEINFO_CMT>
        </FUNCTION>
        <FUNCTION ENTRY_POINT="CODE:0179">
            <ADDRESS_RANGE START="CODE:0179" END="CODE:01A9" />
            <TYPEINFO_CMT>undefined sub_CODE_179()</TYPEINFO_CMT>
        </FUNCTION>
        <FUNCTION ENTRY_POINT="CODE:01AA">
            <ADDRESS_RANGE START="CODE:01AA" END="CODE:01AD" />
            <TYPEINFO_CMT>undefined sub_CODE_1AA()</TYPEINFO_CMT>
        </FUNCTION>
        <FUNCTION ENTRY_POINT="CODE:0206">
            <ADDRESS_RANGE START="CODE:0206" END="CODE:020E" />
            <TYPEINFO_CMT>undefined sub_CODE_206()</TYPEINFO_CMT>
        </FUNCTION>
        <FUNCTION ENTRY_POINT="CODE:039D">
            <ADDRESS_RANGE START="CODE:039D" END="CODE:03A5" />
            <TYPEINFO_CMT>undefined sub_CODE_39D()</TYPEINFO_CMT>
        </FUNCTION>
        <FUNCTION ENTRY_POINT="CODE:04CD">
            <ADDRESS_RANGE START="CODE:04CD" END="CODE:04D5" />
            <TYPEINFO_CMT>undefined sub_CODE_4CD()</TYPEINFO_CMT>
        </FUNCTION>
        <FUNCTION ENTRY_POINT="CODE:0540">
            <ADDRESS_RANGE START="CODE:0540" END="CODE:0548" />
            <TYPEINFO_CMT>undefined sub_CODE_540()</TYPEINFO_CMT>
        </FUNCTION>
        <FUNCTION ENTRY_POINT="CODE:0568">
            <ADDRESS_RANGE START="CODE:0568" END="CODE:0570" />
            <TYPEINFO_CMT>undefined sub_CODE_568()</TYPEINFO_CMT>
        </FUNCTION>
        <FUNCTION ENTRY_POINT="CODE:0590">
            <ADDRESS_RANGE START="CODE:0590" END="CODE:0598" />
            <TYPEINFO_CMT>undefined sub_CODE_590()</TYPEINFO_CMT>
        </FUNCTION>
        <FUNCTION ENTRY_POINT="CODE:05BE">
            <ADDRESS_RANGE START="CODE:05BE" END="CODE:05C6" />
            <TYPEINFO_CMT>undefined sub_CODE_5BE()</TYPEINFO_CMT>
        </FUNCTION>
        <FUNCTION ENTRY_POINT="CODE:05FA">
            <ADDRESS_RANGE START="CODE:05FA" END="CODE:0602" />
            <TYPEINFO_CMT>undefined sub_CODE_5FA()</TYPEINFO_CMT>
        </FUNCTION>
        <FUNCTION ENTRY_POINT="CODE:0639">
            <ADDRESS_RANGE START="CODE:0639" END="CODE:0641" />
            <TYPEINFO_CMT>undefined sub_CODE_639()</TYPEINFO_CMT>
        </FUNCTION>
        <FUNCTION ENTRY_POINT="CODE:0689">
            <ADDRESS_RANGE START="CODE:0689" END="CODE:0691" />
            <TYPEINFO_CMT>undefined sub_CODE_689()</TYPEINFO_CMT>
        </FUNCTION>
        <FUNCTION ENTRY_POINT="CODE:0800">
            <ADDRESS_RANGE START="CODE:0800" END="CODE:0808" />
            <TYPEINFO_CMT>undefined sub_CODE_800()</TYPEINFO_CMT>
        </FUNCTION>
        <FUNCTION ENTRY_POINT="CODE:086E">
            <ADDRESS_RANGE START="CODE:086E" END="CODE:0876" />
            <TYPEINFO_CMT>undefined sub_CODE_86E()</TYPEINFO_CMT>
        </FUNCTION>
        <FUNCTION ENTRY_POINT="CODE:08B8">
            <ADDRESS_RANGE START="CODE:08B8" END="CODE:08C0" />
            <TYPEINFO_CMT>undefined sub_CODE_8B8()</TYPEINFO_CMT>
        </FUNCTION>
        <FUNCTION ENTRY_POINT="CODE:096E">
            <ADDRESS_RANGE START="CODE:096E" END="CODE:0976" />
            <TYPEINFO_CMT>undefined sub_CODE_96E()</TYPEINFO_CMT>
        </FUNCTION>
        <FUNCTION ENTRY_POINT="CODE:0A58">
            <ADDRESS_RANGE START="CODE:0A58" END="CODE:0A64" />
            <TYPEINFO_CMT>undefined sub_CODE_A58()</TYPEINFO_CMT>
        </FUNCTION>
        <FUNCTION ENTRY_POINT="CODE:0A65">
            <ADDRESS_RANGE START="CODE:0A65" END="CODE:0A6A" />
            <TYPEINFO_CMT>undefined sub_CODE_A65()</TYPEINFO_CMT>
        </FUNCTION>
    </FUNCTIONS>
    <MARKUP>
    </MARKUP>
</PROGRAM>